Metadata-Version: 2.1
Name: odoo-addon-account_move_so_import
Version: 16.0.1.0.0.8
Summary: Journal Entry Sale Order completion
Home-page: https://github.com/OCA/account-reconcile
Author: Camptocamp,Odoo Community Association (OCA)
Author-email: support@odoo-community.org
License: AGPL-3
Classifier: Programming Language :: Python
Classifier: Framework :: Odoo
Classifier: Framework :: Odoo :: 16.0
Classifier: License :: OSI Approved :: GNU Affero General Public License v3
Requires-Python: >=3.10
Requires-Dist: odoo-addon-account-move-base-import <16.1dev,>=16.0dev
Requires-Dist: odoo <16.1dev,>=16.0a
